Metadata-Version: 2.1
Name: pysimplecalc
Version: 1
Summary: A simple calculator, able to parse quite complex expressions
Home-page: https://github.com/facundobatista/simplecalc
Author: Facundo Batista
Author-email: facundo@taniquetil.com.ar
License: UNKNOWN
Platform: UNKNOWN
Classifier: Environment :: Console
Classifier: License :: OSI Approved :: Apache Software License
Classifier: Operating System :: OS Independent
Classifier: Programming Language :: Python :: 3
Requires-Python: >=3
